__init__.py
cliserc/simplex.py
cliserc-1.0b2.dist-info/METADATA
cliserc-1.0b2.dist-info/WHEEL
cliserc-1.0b2.dist-info/licenses/LICENSE
cliserc-1.0b2.dist-info/RECORD
