Metadata-Version: 2.1
Name: cliserc
Version: 1.0b2
Summary: Simple client-server communication utility
Project-URL: Homepage, https://github.com/bwilk315/cliserc
Project-URL: License, https://www.apache.org/licenses/LICENSE-2.0.txt
Author-email: bwilk315 <bwilk315@onet.pl>
License-File: LICENSE
Classifier: License :: OSI Approved :: Apache Software License
Classifier: Operating System :: OS Independent
Classifier: Programming Language :: Python :: 3
Requires-Python: >=3.5
